htmx_gen/__init__.py
htmx_gen-1.0.3.dist-info/LICENSE
htmx_gen-1.0.3.dist-info/WHEEL
htmx_gen-1.0.3.dist-info/METADATA
htmx_gen-1.0.3.dist-info/RECORD
